Merkurial_ImageSifter/__init__.py
Merkurial_ImageSifter/buttons.py
Merkurial_ImageSifter/carousel.py
Merkurial_ImageSifter/carousel_helpers.py
Merkurial_ImageSifter/carousel_text.py
Merkurial_ImageSifter/file_handlers.py
Merkurial_ImageSifter/image_sifter.py
Merkurial_ImageSifter/images_viewer.py
Merkurial_ImageSifter/images_viewer_helpers.py
Merkurial_ImageSifter/message_box.py
Merkurial_ImageSifter/update_button.py
Merkurial_ImageSifter-0.0.1.dist-info/LICENSE
Merkurial_ImageSifter-0.0.1.dist-info/METADATA
Merkurial_ImageSifter-0.0.1.dist-info/WHEEL
Merkurial_ImageSifter-0.0.1.dist-info/top_level.txt
Merkurial_ImageSifter-0.0.1.dist-info/RECORD
