Metadata-Version: 2.1
Name: Merkurial_ImageSifter
Version: 0.0.1
Summary: ImageSifter Is Used When You Want To Change The Directories Of Images..
Author-email: Brandon Marcure <brandon@merkurialphoenix.com>
Project-URL: Homepage, https://github.com/ArisenPhoenix/ImageSifter
Project-URL: Bug Tracker, https://github.com/ArisenPhoenix/ImageSifter/issues
Classifier: Programming Language :: Python :: 3
Classifier: License :: OSI Approved :: GNU General Public License (GPL)
Classifier: Operating System :: OS Independent
Requires-Python: >=3.10
License-File: LICENSE
